type_docopt.py
type_docopt-0.8.2.dist-info/LICENSE
type_docopt-0.8.2.dist-info/METADATA
type_docopt-0.8.2.dist-info/WHEEL
type_docopt-0.8.2.dist-info/top_level.txt
type_docopt-0.8.2.dist-info/RECORD
