Metadata-Version: 2.1
Name: type-docopt
Version: 0.8.2
Summary: Pythonic argument parser, with type description.
Home-page: https://github.com/dreamgonfly/type-docopt
Author: Yongrae Jo
Author-email: dreamgonfly@gmail.com
License: MIT
Keywords: arguments parser argparse optparse getopt
Platform: UNKNOWN
Classifier: Development Status :: 4 - Beta
Classifier: Topic :: Utilities
Classifier: Programming Language :: Python :: 3
Classifier: Programming Language :: Python :: 3.6
Classifier: Programming Language :: Python :: 3.7
Classifier: Programming Language :: Python :: 3.8
Classifier: License :: OSI Approved :: MIT License
